{
  "modelo": "LogisticRegression",
  "version": "1.0",
  "fecha_entrenamiento": "2026-06-13",
  "sklearn_version": "1.6.1",
  "random_state": 42,
  "metrica_principal": "f1_score",
  "valor_f1": 0.6667,
  "accuracy": 0.8923,
  "precision": 0.6364,
  "recall": 0.7,
  "auc_roc": 0.8995,
  "variables_entrada": [
    "school",
    "sex",
    "age",
    "address",
    "famsize",
    "Pstatus",
    "Medu",
    "Fedu",
    "Mjob",
    "Fjob",
    "reason",
    "guardian",
    "traveltime",
    "studytime",
    "failures",
    "schoolsup",
    "famsup",
    "paid",
    "activities",
    "nursery",
    "higher",
    "internet",
    "romantic",
    "famrel",
    "freetime",
    "goout",
    "Dalc",
    "Walc",
    "health",
    "absences",
    "G1"
  ],
  "variable_objetivo": "riesgo",
  "comparacion_modelos": {
    "Regresion_Logistica": {
      "f1": 0.6667,
      "accuracy": 0.8923,
      "precision": 0.6364,
      "recall": 0.7,
      "auc_roc": 0.8995
    },
    "Random_Forest": {
      "f1": 0.619,
      "accuracy": 0.8769,
      "precision": 0.5909,
      "recall": 0.65,
      "auc_roc": 0.9018
    },
    "Pipeline_LR_Scaler": {
      "f1": 0.5641,
      "accuracy": 0.8692,
      "precision": 0.5789,
      "recall": 0.55,
      "auc_roc": 0.8923
    }
  },
  "modelo_seleccionado": "LogisticRegression simple",
  "justificacion": "Mayor F1-score (66.7%) sobre conjunto de prueba. Supera a Random Forest y Pipeline con Scaler en deteccion de estudiantes en riesgo.",
  "descripcion": "Clasificacion binaria de riesgo academico. riesgo=1 si G3<10, riesgo=0 si G3>=10",
  "observaciones": "Entrenado con sklearn 1.6.1, semilla 42. Tres modelos comparados."
}